Workbook
Name Adj: Control!$I$13
Name AID: Annual!$N$15
Name DNN: Subscription!$E$19
Name DRN: Subscription!$E$16
Name ID: Factsheet!$P$6
Name Name: Dividend!$E$15
Name Name: Subscription!$E$15
Name Name: #REF!
Name NN: Annual!$E$19
Name RN: Annual!$E$16

Sheet Control
H1: Sector | I1: Percentage
B2: Manager | D2: Mr. Ng Zhi Yao | H2: Technology | I2: 0.7643 | L2: % | M2: 1 Months | N2: 3 Months | O2: 6 Months | P2: 1 Year | Q2: 3 Years | R2: All
B3: Fund Category | D3: Equity Fund | H3: Cash and other assets | I3: 0.236 | L3: Portfolio | M3: =100*((1+_xlfn.XLOOKUP(EOMONTH(ID,0),Data!$A:$A,Data!$B:$B,,-1))/(1+_xlfn.XLOOKUP(EOMONTH(ID,-1),Data!$A:$A,Data!$B:$B,,-1))-1) -> 2.0925207 | N3: =100*((1+_xlfn.XLOOKUP(EOMONTH(ID,0),Data!$A:$A,Data!$B:$B,,-1))/(1+_xlfn.XLOOKUP(EOMONTH(ID,-3),Data!$A:$A,Data!$B:$B,,-1))-1) -> -3.8617352 | O3: =100*((1+_xlfn.XLOOKUP(EOMONTH(ID,0),Data!$A:$A,Data!$B:$B,,-1))/(1+_xlfn.XLOOKUP(EOMONTH(ID,-6),Data!$A:$A,Data!$B:$B,,-1))-1) -> 2.1268522 | P3: =100*((1+_xlfn.XLOOKUP(EOMONTH(ID,0),Data!$A:$A,Data!$B:$B,,-1))/(1+_xlfn.XLOOKUP(EOMONTH(ID,-12),Data!$A:$A,Data!$B:$B,,-1))-1) -> 18.20174 | Q3: =100*((1+_xlfn.XLOOKUP(EOMONTH(ID,0),Data!$A:$A,Data!$B:$B,,-1))/(1+_xlfn.XLOOKUP(EOMONTH(ID,-36),Data!$A:$A,Data!$B:$B,,-1))-1) -> 18.727436 | R3: =100*((1+_xlfn.XLOOKUP(EOMONTH(ID,0),Data!$A:$A,Data!$B:$B,,-1))/(1+_xlfn.XLOOKUP(DATE(2021,12,13),Data!$A:$A,Data!$B:$B,,-1))-1) -> 6.9592072
B4: Launch Date | D4: 44543 | H4: Money Market Fund | I4: 0 | L4: FBMKLCI | M4: =100*((1+_xlfn.XLOOKUP(EOMONTH(ID,0),Data!$A:$A,Data!$C:$C,,-1))/(1+_xlfn.XLOOKUP(EOMONTH(ID,-1),Data!$A:$A,Data!$C:$C,,-1))-1) -> -1.3941225 | N4: =100*((1+_xlfn.XLOOKUP(EOMONTH(ID,0),Data!$A:$A,Data!$C:$C,,-1))/(1+_xlfn.XLOOKUP(EOMONTH(ID,-3),Data!$A:$A,Data!$C:$C,,-1))-1) -> 6.9892239 | O4: =100*((1+_xlfn.XLOOKUP(EOMONTH(ID,0),Data!$A:$A,Data!$C:$C,,-1))/(1+_xlfn.XLOOKUP(EOMONTH(ID,-6),Data!$A:$A,Data!$C:$C,,-1))-1) -> 8.9828077 | P4: =100*((1+_xlfn.XLOOKUP(EOMONTH(ID,0),Data!$A:$A,Data!$C:$C,,-1))/(1+_xlfn.XLOOKUP(EOMONTH(ID,-12),Data!$A:$A,Data!$C:$C,,-1))-1) -> 9.0118753 | Q4: =100*((1+_xlfn.XLOOKUP(EOMONTH(ID,0),Data!$A:$A,Data!$C:$C,,-1))/(1+_xlfn.XLOOKUP(EOMONTH(ID,-36),Data!$A:$A,Data!$C:$C,,-1))-1) -> 18.045785 | R4: =100*((1+_xlfn.XLOOKUP(EOMONTH(ID,0),Data!$A:$A,Data!$C:$C,,-1))/(1+_xlfn.XLOOKUP(DATE(2021,12,13),Data!$A:$A,Data!$C:$C,,-1))-1) -> 14.834165
B5: Unit Net Asset Value (NAV) | D5: 1.0695884 | L5: Tech Index | M5: =100*((1+_xlfn.XLOOKUP(EOMONTH(ID,0),Data!$A:$A,Data!$D:$D,,-1))/(1+_xlfn.XLOOKUP(EOMONTH(ID,-1),Data!$A:$A,Data!$D:$D,,-1))-1) -> -0.64022764 | N5: =100*((1+_xlfn.XLOOKUP(EOMONTH(ID,0),Data!$A:$A,Data!$D:$D,,-1))/(1+_xlfn.XLOOKUP(EOMONTH(ID,-3),Data!$A:$A,Data!$D:$D,,-1))-1) -> -3.0539649 | O5: =100*((1+_xlfn.XLOOKUP(EOMONTH(ID,0),Data!$A:$A,Data!$D:$D,,-1))/(1+_xlfn.XLOOKUP(EOMONTH(ID,-6),Data!$A:$A,Data!$D:$D,,-1))-1) -> 0.59416637 | P5: =100*((1+_xlfn.XLOOKUP(EOMONTH(ID,0),Data!$A:$A,Data!$D:$D,,-1))/(1+_xlfn.XLOOKUP(EOMONTH(ID,-12),Data!$A:$A,Data!$D:$D,,-1))-1) -> 10.546102 | Q5: =100*((1+_xlfn.XLOOKUP(EOMONTH(ID,0),Data!$A:$A,Data!$D:$D,,-1))/(1+_xlfn.XLOOKUP(EOMONTH(ID,-36),Data!$A:$A,Data!$D:$D,,-1))-1) -> -12.621207 | R5: =100*((1+_xlfn.XLOOKUP(EOMONTH(ID,0),Data!$A:$A,Data!$D:$D,,-1))/(1+_xlfn.XLOOKUP(DATE(2021,12,13),Data!$A:$A,Data!$D:$D,,-1))-1) -> -41.30686
B6: Fund Size | D6: =D5*D7 -> 858278.79
B7: Unit in Curculation | D7: 802438.36
B8: Financial Year End | D8: 46356 | H8: PRE SETTING | L8: Year | M8: Description | O8: Distrubution (Sen) | Q8: Payout Ratio
B9: Min. Initial Investment | D9: 10000 | H9: Fit All Rows in one page | L9: 2024 | M9: Interim | O9: 0.5 | Q9: 0.909
B10: Min. Additional Investment | D10: 1000 | L10: 2024 | M10: Final | O10: 1.55 | Q10: 0.2601
B11: Benchmark | D11: FBMKLCI , Tech Index | L11: 2025 | M11: Interim | O11: 2.1 | Q11: 0.798
B12: Annual Management Fee | D12: 0.10% p.a. of NAV | L12: 2025 | M12: Final | O12: 1 | Q12: 0.119
B13: Perfromance Fee | D13: 10.0% p.a. of excess return | H13: Adj | I13: 1
B14: Distribution Policy | D14: At least 80% of gross income
H18: =22.9/D6*100 -> 0.0026681307

Sheet Data
A1: Date | B1: Fund Return | C1: KLCI Return | D1: TECH Return
A2: 44543 | B2: 0 | C2: 0 | D2: 0
A3: 44544 | B3: -2.8070175e-05 | C3: -0.009325288 | D3: -0.0026263263
A4: 44545 | B4: -5.6140351e-05 | C4: -0.0080609555 | D4: -0.0012606366
A5: 44546 | B5: -8.4210526e-05 | C5: -0.0068367606 | D5: 0.0014707427
A6: 44547 | B6: -0.21179474 | C6: 0.0047830566 | D6: -0.0087194033
A7: 44550 | B7: -0.14659825 | C7: -0.00064220061 | D7: -0.018804496
A8: 44551 | B8: -0.19679649 | C8: -0.0015185369 | D8: -0.014497321
A9: 44552 | B9: -0.17331053 | C9: 0.003652516 | D9: -0.01239626
A10: 44553 | B10: -0.16670351 | C10: 0.014422755 | D10: -0.0037819099
A11: 44554 | B11: -0.16141716 | C11: 0.014442824 | D11: -0.0031515916
A12: 44557 | B12: -0.14593218 | C12: 0.026122848 | D12: 0.00042021221
A13: 44558 | B13: -0.13348666 | C13: 0.030123222 | D13: 0.016283223
... A1102: 46083 | B1102: 0.03468751 | C1102: 0.13711652 | D1102: -0.4302973

Sheet D2
A1: Date | B1: Fund | C1: FBMKLCI | D1: Tech Index
A2: {=_xlfn._xlws.FILTER(Data!A2:D3650,(Data!A2:A3650<=EOMONTH(ID,0))*(Data!A2:A3650<>""))} -> 44543 | B2: 0 | C2: 0 | D2: 0
A3: 44544 | B3: -2.8070175e-05 | C3: -0.009325288 | D3: -0.0026263263
A4: 44545 | B4: -5.6140351e-05 | C4: -0.0080609555 | D4: -0.0012606366
A5: 44546 | B5: -8.4210526e-05 | C5: -0.0068367606 | D5: 0.0014707427
A6: 44547 | B6: -0.21179474 | C6: 0.0047830566 | D6: -0.0087194033
A7: 44550 | B7: -0.14659825 | C7: -0.00064220061 | D7: -0.018804496
A8: 44551 | B8: -0.19679649 | C8: -0.0015185369 | D8: -0.014497321
A9: 44552 | B9: -0.17331053 | C9: 0.003652516 | D9: -0.01239626
A10: 44553 | B10: -0.16670351 | C10: 0.014422755 | D10: -0.0037819099
A11: 44554 | B11: -0.16141716 | C11: 0.014442824 | D11: -0.0031515916
A12: 44557 | B12: -0.14593218 | C12: 0.026122848 | D12: 0.00042021221
A13: 44558 | B13: -0.13348666 | C13: 0.030123222 | D13: 0.016283223
A14: 44559 | B14: -0.12709045 | C14: 0.033568361 | D14: 0.016913541
... A1101: 46080 | B1101: 0.069592072 | C1101: 0.14834165 | D1101: -0.4130686

Sheet Investor Data
A1: Account ID | B1: Account Type | C1: Registered Name | D1: Nominee | E1: Holding Units | F1: Total Cost | G1: Latest Price | H1: Realized | I1: Dividend Recd | J1: Issued Date | K1: Phone | L1: Email | M1: Settlement | N1: Bank Name | O1: Bank Acc | P1: Address | Q1: Taman | R1: Postcode
A2: =LEFT(InvProfile[[#This Row],[Account Type]],1)&"A00"&RIGHT(YEAR(InvProfile[[#This Row],[Issued Date]]),2)&TEXT(MONTH(InvProfile[[#This Row],[Issued Date]]),"00")&TEXT(DAY(InvProfile[[#This Row],[Issued Date]]),"00") -> DA00211213 | B2: Direct Account | C2: Ng Zhi Yao | D2: - | E2: 265199.5 | F2: 237370.97 | G2: 1.1125483 | H2: 1917.07 | I2: 5436.59 | J2: 44543 | K2: (+60)11 - 1121 8085 | L2: ngzy0825@gmail.com | M2: Banking | N2: Hong Leong Bank | O2: 219 5015 0638 | P2: No.19 Jalan Rusa | Q2: Taman Mohammad Yassin | R2: 86200 Simpang Renggam
A3: =LEFT(InvProfile[[#This Row],[Account Type]],1)&"A00"&RIGHT(YEAR(InvProfile[[#This Row],[Issued Date]]),2)&TEXT(MONTH(InvProfile[[#This Row],[Issued Date]]),"00")&TEXT(DAY(InvProfile[[#This Row],[Issued Date]]),"00") -> NA00230817 | B3: Nominee Account | C3: Ng Mon Teng | D3: Ng Zhi Hui | E3: 31256.33 | F3: 30000 | G3: 1.1125483 | H3: 0 | J3: 45155 | K3: (+60)12 - 7188 288 | L3: osaka88@gmail.com | M3: Banking | N3: RHB Bank | O3: 2013 1630 0173 90 | P3: No.19 Jalan Rusa | Q3: Taman Mohammad Yassin | R3: 86200 Simpang Renggam
A4: =LEFT(InvProfile[[#This Row],[Account Type]],1)&"A00"&RIGHT(YEAR(InvProfile[[#This Row],[Issued Date]]),2)&TEXT(MONTH(InvProfile[[#This Row],[Issued Date]]),"00")&TEXT(DAY(InvProfile[[#This Row],[Issued Date]]),"00") -> DA00230814 | B4: Direct Account | C4: Ng Xin Yu | D4: - | E4: 39223.262 | F4: 40000 | G4: 1.1125483 | H4: 0 | J4: 45152 | K4: (+65) 8063 9855 | L4: ngxy2004@gmail.com | M4: Banking | N4: Public Bank | O4: 5048 9996 06 | P4: No.19 Jalan Rusa | Q4: Taman Mohammad Yassin | R4: 86200 Simpang Renggam
A5: =LEFT(InvProfile[[#This Row],[Account Type]],1)&"A00"&RIGHT(YEAR(InvProfile[[#This Row],[Issued Date]]),2)&TEXT(MONTH(InvProfile[[#This Row],[Issued Date]]),"00")&TEXT(DAY(InvProfile[[#This Row],[Issued Date]]),"00") -> NA00230818 | B5: Nominee Account | C5: Ng Mon Teng | D5: Siah Lih Ling | E5: 176104.25 | F5: 180000 | G5: 1.1125483 | H5: 0 | J5: 45156 | K5: (+60)12 - 7188 288 | L5: osaka88@gmail.com | M5: Banking | N5: RHB Bank | O5: 2013 1630 0173 90 | P5: No.19 Jalan Rusa | Q5: Taman Mohammad Yassin | R5: 86200 Simpang Renggam
A6: =LEFT(InvProfile[[#This Row],[Account Type]],1)&"A00"&RIGHT(YEAR(InvProfile[[#This Row],[Issued Date]]),2)&TEXT(MONTH(InvProfile[[#This Row],[Issued Date]]),"00")&TEXT(DAY(InvProfile[[#This Row],[Issued Date]]),"00") -> DA00231102 | B6: Direct Account | C6: Siah Kim Teck | D6: - | E6: 99388.359 | F6: 100000 | G6: 1.1125483 | H6: 0 | I6: 2037.46 | J6: 45232 | K6: (+60)19 - 7781 376 | L6: - | M6: Cash Settlement | N6: - | O6: - | P6: No.2 Jalan Austin Heights 2/11 | Q6: Taman Mount Austin | R6: 81100 Johor Bahru
A7: =LEFT(InvProfile[[#This Row],[Account Type]],1)&"A00"&RIGHT(YEAR(InvProfile[[#This Row],[Issued Date]]),2)&TEXT(MONTH(InvProfile[[#This Row],[Issued Date]]),"00")&TEXT(DAY(InvProfile[[#This Row],[Issued Date]]),"00") -> JA00250407 | B7: Joint Account | C7: Siah Woei Sin & Siah Woei Pyng | D7: 1 : 1 | E7: 55067.72 | F7: 45000 | G7: 1.1125483 | H7: 0 | J7: 45754 | K7: (+60)16 - 709 6000 | L7: kensiah@live.com | M7: Banking | N7: Malayan Bank | O7: 1012 8000 3953 | P7: No.2 Jalan Austin Heights 2/11 | Q7: Taman Mount Austin | R7: 81100 Johor Bahru
A8: =LEFT(InvProfile[[#This Row],[Account Type]],1)&"A00"&RIGHT(YEAR(InvProfile[[#This Row],[Issued Date]]),2)&TEXT(MONTH(InvProfile[[#This Row],[Issued Date]]),"00")&TEXT(DAY(InvProfile[[#This Row],[Issued Date]]),"00") -> DA00231129 | B8: Direct Account | C8: Ng Zhi Yao © | D8: - | E8: 4413.0509 | F8: 5000 | G8: 1.1125483 | H8: 0 | J8: 45259 | K8: (+60)11 - 1121 8085 | L8: nzy.invest@gmail.com | M8: Banking | N8: Hong Leong Bank | O8: 219 5015 0638 | P8: No.19 Jalan Rusa | Q8: Taman Mohammad Yassin | R8: 86200 Simpang Renggam
A9: =LEFT(InvProfile[[#This Row],[Account Type]],1)&"A00"&RIGHT(YEAR(InvProfile[[#This Row],[Issued Date]]),2)&TEXT(MONTH(InvProfile[[#This Row],[Issued Date]]),"00")&TEXT(DAY(InvProfile[[#This Row],[Issued Date]]),"00") -> DA00260313 | B9: Direct Account | C9: Ng Mon Teng | D9: - | E9: 38228.081 | F9: 38000 | G9: 0.99403368 | H9: 0 | I9: 0 | J9: 46094 | K9: (+60)12 - 7188 288 | L9: osaka88@gmail.com | M9: Banking | N9: RHB Bank | O9: 2013 1630 0173 90 | P9: No.19 Jalan Rusa | Q9: Taman Mohammad Yassin | R9: 86200 Simpang Renggam

Sheet Factsheet
A1: #VALUE!
A6: ZY Family Vision Portfolio | P6: 46054
A8: The portfolio aims to provide our investors ("family members") with a capital appreciation that is potentially higher than the prevailing fixed-deposit rate by investing in high-growth portfolio of stock and fixed income instruments.
A11: ="Fund Details as at " & TEXT(EOMONTH(P6,0),"dd mmmm yyy") -> Fund Details as at 28 February 2026 | K11: ="Sector Allocation* as at "& TEXT(EOMONTH(P6,0),"dd MMMM yyy") -> Sector Allocation* as at 28 February 2026
K23: *As percentage Net Asset Value (NAV) of the fund.
A25: Investment Strategy: | K25: ="Portfolio Performance Analysis as at "& TEXT(EOMONTH(P6,0),"dd mmmm yyy") -> Portfolio Performance Analysis as at 28 February 2026
A31: Distribution History:
A38: Manager's Comments:
K42: ="Largest Holdings* as at "& TEXT(EOMONTH(P6,0),"dd mmmm yyy") -> Largest Holdings* as at 28 February 2026
K43: Asset Name | Q43: Percentage
K44: Zetrix AI Berhad ( f.k.a. MYEG ) | Q44: 0.764
K47: * As percentage Net Asset Value (NAV) of the fund ^ Derivatives: Warrant Securities
A51: Disclaimer:
A52: Investment involves significant risk, including the potential loss of principal. Past performance is not indicative of future results, and market volatility may affect the timing of realized gains. Please note that this portfolio update is intended strictly for family members only; it does not constitute a financial prospectus and is not open to the general public or external investors.
A57: Head Office: None | G57: Line: (60)11-1121 8085 Email: nzy.invest@gmail.com Website: #N/A

Sheet Annual
A1: #VALUE! | T1: #VALUE!
K5: INVESTMENT ACCOUNT STATEMENT | AD5: INVESTMENT ACCOUNT STATEMENT
L7: Page No. | O7: : 1 of 2 | AE7: Page No. | AH7: : 2 of 2
A8: =UPPER(RN) -> SIAH WOEI SIN & SIAH WOEI PYNG | L8: Issued Date | O8: =": " & TEXT(TODAY(),"dd-mm-yyy") -> : 19-07-2026 | T8: =A8 -> SIAH WOEI SIN & SIAH WOEI PYNG | AE8: Issued Date | AH8: =O8 -> : 19-07-2026
A9: =_xlfn.XLOOKUP(RN,InvProfile[Registered Name],InvProfile[Address]) -> No.2 Jalan Austin Heights 2/11 | L9: Statement Type | O9: : Annually | T9: =A9 -> No.2 Jalan Austin Heights 2/11 | AE9: Statement Type | AH9: =O9 -> : Annually
A10: =_xlfn.XLOOKUP(RN,InvProfile[Registered Name],InvProfile[Taman]) -> Taman Mount Austin | L10: Statement Period | O10: : 1/12/2024 - 30/11/2025 | T10: =A10 -> Taman Mount Austin | AE10: Statement Period | AH10: =O10 -> : 1/12/2024 - 30/11/2025
A11: =_xlfn.XLOOKUP(RN,InvProfile[Registered Name],InvProfile[Postcode]) -> 81100 Johor Bahru | L11: Email Address | O11: : nzy.invest@gmail.com | T11: =A11 -> 81100 Johor Bahru | AE11: Email Address | AH11: =O11 -> : nzy.invest@gmail.com
L12: Telephone No. | O12: : (+60)11 - 1121 8085 | AE12: Telephone No. | AH12: =O12 -> : (+60)11 - 1121 8085
A14: Investor's Information | T14: Principal Transaction
A15: Account Type | E15: =_xlfn.XLOOKUP(RN,InvProfile[Registered Name],InvProfile[Account Type]) -> Joint Account | J15: Account ID | N15: {=_xlfn._xlws.FILTER(InvProfile[Account ID],(InvProfile[Registered Name]=RN)*(InvProfile[Nominee]=NN))} -> #VALUE! | T15: Date | W15: Description | Z15: Cashflow @ Price | AC15: Avg.Cost (RM) | AF15: Units Issued | AI15: Units Balanced
A16: Registered Name | E16: Siah Woei Sin & Siah Woei Pyng | J16: Settlement Type | N16: =_xlfn.XLOOKUP(RN,InvProfile[Registered Name],InvProfile[Settlement]) -> Banking | T16: 45627 | W16: Opening | AI16: =G23 -> #VALUE!
A17: Phone No. | E17: =_xlfn.XLOOKUP(RN,InvProfile[Registered Name],InvProfile[Phone]) -> (+60)16 - 709 6000 | J17: Bank Name | N17: =_xlfn.XLOOKUP(RN,InvProfile[Registered Name],InvProfile[Bank Name]) -> Malayan Bank | T17: 45991 | W17: Closing | AI17: =G23 -> #VALUE!
A18: Email Address | E18: =_xlfn.XLOOKUP(RN,InvProfile[Registered Name],InvProfile[Email]) -> kensiah@live.com | J18: Bank Account No. | N18: =_xlfn.XLOOKUP(RN,InvProfile[Registered Name],InvProfile[Bank Acc]) -> 1012 8000 3953
A19: =IF(LEFT(E15,1)="j","Joint Proportion","Nominee Name") -> Joint Proportion | E19: 50% : 50% | J19: Total Days Held | N19: {=TEXT(DATE(2025,11,30)-_xlfn._xlws.FILTER(InvProfile[Issued Date],(InvProfile[Registered Name]=RN)*(InvProfile[Nominee]=NN)),"#,##0") & " days"} -> #VALUE! | T19: Dividend Transaction
T20: Date | W20: Description | AA20: DPS | AC20: Holding Units | AF20: Dividend Amount | AI20: Balanced (RM)
A21: Account Summary | T21: 45627 | W21: Opening | AI21: 0
A22: Fields | G22: Holding Units | K22: Average Price | O22: Total Value (RM) | T22: 45658 | W22: FY24 Dividend - Interim | AA22: 0.5 | AC22: =G23 -> #VALUE! | AF22: =AA22*AC22/100 -> #VALUE! | AI22: =AF22+AI21 -> #VALUE!
A23: ( a ) | C23: Latest Fund Price | G23: =_xlfn.XLOOKUP(AID,InvProfile[Account ID],InvProfile[Holding Units]) -> #VALUE! | K23: =_xlfn.XLOOKUP(AID,InvProfile[Account ID],InvProfile[Latest Price]) -> #VALUE! | O23: =ROUND(G23*K23,2) -> #VALUE! | T23: 45689 | W23: FY24 Dividend - Final | AA23: 1.55 | AC23: =AC22 -> #VALUE! | AF23: =AA23*AC23/100 -> #VALUE! | AI23: =AF23+AI22 -> #VALUE!
A24: ( b ) | C24: Subscription Cost | G24: =G23 -> #VALUE! | K24: =ABS(O24/G24) -> #VALUE! | O24: =-_xlfn.XLOOKUP(AID,InvProfile[Account ID],InvProfile[Total Cost]) -> #VALUE! | T24: 45991 | W24: Closing | AI24: =AF24+AI23 -> #VALUE!
A25: ( c ) | D25: Unrealized Profit & Loss: ( a ) + ( b ) | O25: =O23+O24 -> #VALUE!
A26: ( d ) | D26: Realized Profit & Loss | O26: =_xlfn.XLOOKUP(AID,InvProfile[Account ID],InvProfile[Realized]) -> #VALUE!
A27: ( e ) | D27: Dividend Received | O27: =AI24 -> #VALUE!
A28: ( f ) | D28: Adjustment: #N/A | O28: -15000
A29: Total Profit & Loss: ( c ) + ( d ) + ( e ) + ( f ) | O29: =SUM(O25:S28) -> #VALUE!
A30: Total Performance % | O30: =-O29/O24 -> #VALUE! | T30: IMPORTANT NOTICES
A31: Annualized Performance* % | O31: -
A32: *Powered by Financial Formulation of Internal Rate of Return (IRR) & Mathematical Algorithm Newton's method
A35: Head Office: None | G35: Line: (60)11-1121 8085 Email: nzy.invest@gmail.com Website: #N/A | T35: Head Office: None | Z35: Line: (60)11-1121 8085 Email: nzy.invest@gmail.com Website: #N/A

Sheet Subscription
A1: #VALUE!
K5: FUND SUBSCRIPTION STATEMENT
L7: Page No. | O7: : 1 of 1
A8: =UPPER(DRN) -> NG MON TENG | L8: Issued Date | O8: =": " & TEXT(TODAY(),"dd-mm-yyy") -> : 19-07-2026
A9: =_xlfn.XLOOKUP(DRN,InvProfile[Registered Name],InvProfile[Address]) -> No.19 Jalan Rusa | L9: Statement Type | O9: : Daily Statement
A10: =_xlfn.XLOOKUP(DRN,InvProfile[Registered Name],InvProfile[Taman]) -> Taman Mohammad Yassin | L10: Statement Period | O10: =TODAY()-Adj -> 46221
A11: =_xlfn.XLOOKUP(DRN,InvProfile[Registered Name],InvProfile[Postcode]) -> 86200 Simpang Renggam | L11: Email Address | O11: : nzy.invest@gmail.com
L12: Telephone No. | O12: : (+60)11 - 1121 8085
A14: Investor's Information
A15: Account Type | E15: =_xlfn.XLOOKUP(DRN,InvProfile[Registered Name],InvProfile[Account Type]) -> Nominee Account | J15: Account ID | N15: {=_xlfn._xlws.FILTER(InvProfile[Account ID],(InvProfile[Registered Name]=DRN)*(InvProfile[Nominee]=DNN))} -> DA00260313
A16: Registered Name | E16: Ng Mon Teng | J16: Settlement Type | N16: =_xlfn.XLOOKUP(DRN,InvProfile[Registered Name],InvProfile[Settlement]) -> Banking
A17: Phone No. | E17: =_xlfn.XLOOKUP(DRN,InvProfile[Registered Name],InvProfile[Phone]) -> (+60)12 - 7188 288 | J17: Bank Name | N17: =_xlfn.XLOOKUP(DRN,InvProfile[Registered Name],InvProfile[Bank Name]) -> RHB Bank
A18: Email Address | E18: =_xlfn.XLOOKUP(DRN,InvProfile[Registered Name],InvProfile[Email]) -> osaka88@gmail.com | J18: Bank Account No. | N18: =_xlfn.XLOOKUP(DRN,InvProfile[Registered Name],InvProfile[Bank Acc]) -> 2013 1630 0173 90
A19: =IF(LEFT(E15,1)="j","Joint Ratio","Nominee Name") -> Nominee Name | E19: - | J19: Total Days Held | N19: {=TEXT(TODAY()-_xlfn._xlws.FILTER(InvProfile[Issued Date],(InvProfile[Registered Name]=DRN)*(InvProfile[Nominee]=DNN))-Adj,"#,##0") & " days"} -> 127 days
A21: Principal Transaction
A22: Date | D22: Description | G22: Investment Value | J22: Subscription Price | M22: Unit Balanced | P22: Average Cost
A23: =TODAY()-Adj -> 46221 | D23: Opening | G23: 0 | J23: - | M23: 0 | P23: 0
A24: =TODAY()-Adj -> 46221 | D24: Fund Subscription | G24: 38000 | J24: 0.99403368 | M24: =G24/J24 -> 38228.081 | P24: -
A25: =TODAY()-Adj -> 46221 | D25: Closing | G25: =G23+G24 -> 38000 | J25: - | M25: =M23+M24 -> 38228.081 | P25: =G25/M25 -> 0.99403368
A30: IMPORTANT NOTICES
A35: Head Office: None | G35: Line: (60)11-1121 8085 Email: nzy.invest@gmail.com Website: #N/A

Sheet Dividend
A1: #VALUE!
K5: DIVIDEND PAYMENT STATEMENT
L7: Page No. | O7: : 1 of 1
A8: =UPPER(Name) -> NG ZHI YAO | L8: Issued Date | O8: =": " & TEXT(TODAY(),"dd-mm-yyy") -> : 19-07-2026
A9: =_xlfn.XLOOKUP(Name,InvProfile[Registered Name],InvProfile[Address]) -> No.19 Jalan Rusa | L9: Statement Type | O9: : #N/A
A10: =_xlfn.XLOOKUP(Name,InvProfile[Registered Name],InvProfile[Taman]) -> Taman Mohammad Yassin | L10: Statement Period | O10: : 12/12/2025
A11: =_xlfn.XLOOKUP(Name,InvProfile[Registered Name],InvProfile[Postcode]) -> 86200 Simpang Renggam | L11: Email Address | O11: : nzy.invest@gmail.com
L12: Telephone No. | O12: : (+60)11 - 1121 8085
A14: Investor's Information
A15: Investor's Name | E15: Ng Zhi Yao | J15: Settlement Type | N15: =_xlfn.XLOOKUP(Name,InvProfile[Registered Name],InvProfile[Settlement]) -> Banking
A16: Phone Number | E16: =_xlfn.XLOOKUP(Name,InvProfile[Registered Name],InvProfile[Phone]) -> (+60)11 - 1121 8085 | J16: Bank Name | N16: =_xlfn.XLOOKUP(Name,InvProfile[Registered Name],InvProfile[Bank Name]) -> Hong Leong Bank
A17: Email Address | E17: =_xlfn.XLOOKUP(Name,InvProfile[Registered Name],InvProfile[Email]) -> ngzy0825@gmail.com | J17: Bank Account No. | N17: =_xlfn.XLOOKUP(Name,InvProfile[Registered Name],InvProfile[Bank Acc]) -> 219 5015 0638
A19: Dividend Details
A20: Date | D20: Description | G20: Holding Units | J20: EPS | L20: DPR | N20: DPS | P20: Dividend Amount
A21: 46003 | D21: Interim Dividend | G21: 265199.5 | J21: 2.63 | L21: =N21/J21 -> 0.79847909 | N21: 2.1 | P21: =G21*N21/100 -> 5569.1895
A22: 46003 | D22: Final Dividend | G22: =G21 -> 265199.5 | J22: 8.38 | L22: =N22/J22 -> 0.11933174 | N22: 1 | P22: =G22*N22/100 -> 2651.995
A23: Total | N23: =N21+N22 -> 3.1 | P23: =P21+P22 -> 8221.1845
A24: Notes: EPS: Earning Per Share ; DPR: Dividend Payout Ratio ; DPS: Dividend Per Share
A30: IMPORTANT NOTICES
A35: Head Office: None | G35: Line: (60)11-1121 8085 Email: nzy.invest@gmail.com Website: #N/A
